td_ml_probabilistic_unification/__init__.py
td_ml_probabilistic_unification/data_loader.py
td_ml_probabilistic_unification/get_cluster.py
td_ml_probabilistic_unification/get_similarity.py
td_ml_probabilistic_unification/main.py
td_ml_probabilistic_unification-0.0.24.dist-info/METADATA
td_ml_probabilistic_unification-0.0.24.dist-info/WHEEL
td_ml_probabilistic_unification-0.0.24.dist-info/licenses/LICENSE
td_ml_probabilistic_unification-0.0.24.dist-info/RECORD
