Metadata-Version: 2.4
Name: td_ml_probabilistic_unification
Version: 0.0.24
Summary: Probabilistic Unification
Project-URL: Homepage, https://github.com/treasure-data-ps/td_ml_libraries/tree/main/td_ml_probailistic_unification
Project-URL: Bug Tracker, https://github.com/treasure-data-ps/td_ml_libraries/tree/main/td_ml_probailistic_unification
Author-email: Gurbaksh Sharma <gurumail10@gmail.com>
License: Copyright © 2022 Treasure Data, Inc. (or its affiliates). All rights reserved
License-File: LICENSE
Classifier: Operating System :: OS Independent
Classifier: Programming Language :: Python :: 3
Requires-Python: >=3.8
